cavespeak/__init__.py
cavespeak/main.py
cavespeak-0.1.1.dist-info/LICENSE
cavespeak-0.1.1.dist-info/METADATA
cavespeak-0.1.1.dist-info/WHEEL
cavespeak-0.1.1.dist-info/RECORD
